adaptivebridge/__init__.py
adaptivebridge/adaptivebridge.py
adaptivebridge/utils/__init__.py
adaptivebridge/utils/_data_distribution.py
adaptivebridge/utils/_data_validation.py
adaptivebridge/utils/_error_handler.py
adaptivebridge/utils/_metrics.py
adaptivebridge-1.1.0.dist-info/LICENSE
adaptivebridge-1.1.0.dist-info/METADATA
adaptivebridge-1.1.0.dist-info/WHEEL
adaptivebridge-1.1.0.dist-info/top_level.txt
adaptivebridge-1.1.0.dist-info/zip-safe
adaptivebridge-1.1.0.dist-info/RECORD
