Metadata-Version: 2.1
Name: adaptivebridge
Version: 1.1.0
Summary: Revolutionizing ML adaptive modelling for handling missing features and data. The model can predict missing data in real-world scenarios.
Home-page: https://github.com/inetanel/adaptivebridge
Author: Netanel Eliav
Author-email: netanel.eliav@gmail.com
License: MIT
Project-URL: Author Website, https://inetanel.com
Project-URL: Documentation, https://inetanel.github.io/adaptivebridge
Project-URL: Changelog, https://github.com/iNetanel/adaptivebridge/blob/main/CHANGELOG.md
Project-URL: Source Code, https://github.com/inetanel/adaptivebridge
Project-URL: Issue Tracker, https://github.com/inetanel/adaptivebridge/issues
Keywords: sklearn,scikit-learn,python,data analysis,machine learning,data visualization,python library,data processing,data science,data exploration,data manipulation,analytics,statistics,artificial intelligence,AI,feature engineering,data preprocessing,predictive modeling,classification,regression,missing data,data cleaning,data imputation,data quality,missing data analysis,data handling,data integrity,data cleansing,data wrangling,data validation,data completeness,impute missing values,data mi
Classifier: Development Status :: 5 - Production/Stable
Classifier: Intended Audience :: Developers
Classifier: Intended Audience :: Science/Research
Classifier: Intended Audience :: Information Technology
Classifier: Intended Audience :: System Administrators
Classifier: Intended Audience :: Education
Classifier: License :: OSI Approved :: MIT License
Classifier: Programming Language :: Python :: 3.7
Classifier: Programming Language :: Python :: 3.8
Classifier: Programming Language :: Python :: 3.9
Classifier: Programming Language :: Python :: 3.10
Classifier: Programming Language :: Python :: 3.11
Requires-Python: >=3.7
License-File: LICENSE
Requires-Dist: distfit ==1.7.3
Requires-Dist: matplotlib ==3.8.0
Requires-Dist: numpy ==1.26.3
Requires-Dist: pandas ==2.2.0
Requires-Dist: pytest ==7.4.0
Requires-Dist: scikit-learn ==1.3.2
Requires-Dist: scipy ==1.12.0
Requires-Dist: setuptools ==68.2.2
Requires-Dist: tqdm ==4.66.1
Provides-Extra: dev
Requires-Dist: pytest >=7.4.2 ; extra == 'dev'
Requires-Dist: twine >4.0.2 ; extra == 'dev'
